politikontroller_app/__init__.py
politikontroller_app/__main__.py
politikontroller_app/conftest.py
politikontroller_app/db/base.py
politikontroller_app/db/dao.py
politikontroller_app/db/meta.py
politikontroller_app/db/models/__init__.py
politikontroller_app/db/models/access_token.py
politikontroller_app/db/utils.py
politikontroller_app/logging.py
politikontroller_app/settings.py
politikontroller_app/shared/__init__.py
politikontroller_app/shared/dependencies.py
politikontroller_app/shared/responses.py
politikontroller_app/tests/__init__.py
politikontroller_app/tests/test_politikontroller_app.py
politikontroller_app/web/__init__.py
politikontroller_app/web/api/__init__.py
politikontroller_app/web/api/monitoring/__init__.py
politikontroller_app/web/api/monitoring/views.py
politikontroller_app/web/api/police_controls/__init__.py
politikontroller_app/web/api/police_controls/views.py
politikontroller_app/web/api/router.py
politikontroller_app/web/api/user/__init__.py
politikontroller_app/web/api/user/views.py
politikontroller_app/web/application.py
politikontroller_app/web/lifetime.py
politikontroller_app-1.0.1.dist-info/LICENSE
politikontroller_app-1.0.1.dist-info/METADATA
politikontroller_app-1.0.1.dist-info/WHEEL
politikontroller_app-1.0.1.dist-info/entry_points.txt
politikontroller_app-1.0.1.dist-info/RECORD
